rportion/__init__.py
rportion/rportion.py
rportion-0.2.0.dist-info/LICENSE
rportion-0.2.0.dist-info/METADATA
rportion-0.2.0.dist-info/WHEEL
rportion-0.2.0.dist-info/top_level.txt
rportion-0.2.0.dist-info/RECORD
