Metadata-Version: 2.1
Name: rportion
Version: 0.2.0
Summary: Python data structure and operations for 2-dimensional rectilinear polygons
Home-page: https://github.com/tilmann-bartsch/rportion
Author: Tilmann Bartsch
License: MIT
Keywords: rectangle polygon interval-tree
Classifier: License :: OSI Approved :: MIT License
Classifier: Programming Language :: Python :: 3
Classifier: Intended Audience :: Developers
Classifier: Intended Audience :: Information Technology
Classifier: Intended Audience :: Science/Research
Classifier: Operating System :: OS Independent
Requires-Python: >=3.9
License-File: LICENSE
Requires-Dist: sortedcontainers ~=2.2
Requires-Dist: portion ~=2.4.2
Provides-Extra: docu
Requires-Dist: numpy ~=1.26.4 ; extra == 'docu'
Requires-Dist: matplotlib ~=3.5.2 ; extra == 'docu'
Requires-Dist: imageio ~=2.19.5 ; extra == 'docu'
Requires-Dist: pillow ~=9.2.0 ; extra == 'docu'
Requires-Dist: tqdm ~=4.64.0 ; extra == 'docu'
Provides-Extra: test
Requires-Dist: pytest ~=7.0 ; extra == 'test'
Requires-Dist: coverage ~=6.0 ; extra == 'test'
Requires-Dist: numpy ~=1.26.4 ; extra == 'test'
